opentrustprotocol-3.0.0.dist-info/licenses/LICENSE
otp/__init__.py
otp/conformance.py
otp/fuse.py
otp/judgment.py
otp/judgment_id.py
otp/mapper/__init__.py
otp/mapper/boolean.py
otp/mapper/categorical.py
otp/mapper/numerical.py
otp/mapper/registry.py
otp/mapper/types.py
otp/mapper/validation.py
opentrustprotocol-3.0.0.dist-info/METADATA
opentrustprotocol-3.0.0.dist-info/WHEEL
opentrustprotocol-3.0.0.dist-info/top_level.txt
opentrustprotocol-3.0.0.dist-info/RECORD
