Metadata-Version: 2.4
Name: opentrustprotocol
Version: 3.0.0
Summary: 🐍 Official Python SDK for OpenTrust Protocol - The mathematical embodiment of trust itself. Features neutrosophic judgments, fusion operators, OTP mappers, REVOLUTIONARY Conformance Seals, and Performance Oracle with Circle of Trust for real-world outcome tracking.
Author-email: OpenTrust Protocol Team <contact@opentrustprotocol.com>
License: MIT License
Project-URL: Homepage, https://opentrustprotocol.com
Project-URL: Documentation, https://opentrustprotocol.com
Project-URL: Repository, https://github.com/draxork/opentrustprotocol
Keywords: neutrosophy,neutrosophic,uncertainty,trust,audit,ai,otp,conformance-seal,cryptography,proof,performance-oracle,circle-of-trust,outcome-tracking
Classifier: Development Status :: 5 - Production/Stable
Classifier: Intended Audience :: Developers
Classifier: Intended Audience :: Science/Research
Classifier: License :: OSI Approved :: MIT License
Classifier: Operating System :: OS Independent
Classifier: Programming Language :: Python :: 3
Classifier: Programming Language :: Python :: 3.8
Classifier: Programming Language :: Python :: 3.9
Classifier: Programming Language :: Python :: 3.10
Classifier: Programming Language :: Python :: 3.11
Classifier: Topic :: Scientific/Engineering
Classifier: Topic :: Software Development :: Libraries :: Python Modules
Classifier: Topic :: Security
Requires-Python: >=3.8
License-File: LICENSE
Dynamic: license-file
